ragql/__init__.py
ragql/cli.py
ragql/config.py
ragql/core.py
ragql/embeddings.py
ragql/loaders/__init__.py
ragql/loaders/json_logs.py
ragql/loaders/sqlite_events.py
ragql/loaders/text_files.py
ragql/storage.py
ragql-0.2.0.dist-info/entry_points.txt
ragql-0.2.0.dist-info/METADATA
ragql-0.2.0.dist-info/WHEEL
ragql-0.2.0.dist-info/RECORD
