Metadata-Version: 2.3
Name: ragql
Version: 0.2.0
Summary: This project implements a local-first RAG chat system that reads and processes various text-based log files. It splits the content into manageable chunks, generates embeddings using Ollama or OpenAI, and allows users to interactively query the logs for specific information. The application features a customizable response format and supports configuration for user preferences.
Author: Cristian Camargo Filho
Author-email: ccf@cdone.com.br
Requires-Python: >=3.10,<4.0
Classifier: Programming Language :: Python :: 3
Classifier: Programming Language :: Python :: 3.10
Classifier: Programming Language :: Python :: 3.11
Classifier: Programming Language :: Python :: 3.12
Classifier: Programming Language :: Python :: 3.13
Requires-Dist: faiss-cpu (>=1.11,<2.0)
Requires-Dist: numpy (>=2.2.6,<3.0.0)
Requires-Dist: ollama (>=0.4.8,<0.5.0)
Requires-Dist: openai (>=1.25,<2.0)
Requires-Dist: pandas (>=2.2,<3.0)
Requires-Dist: python-dotenv (>=1.1.0,<2.0.0)
Requires-Dist: requests (>=2.32,<3.0)
Requires-Dist: tabulate (>=0.9,<0.10)
Requires-Dist: tqdm (>=4.67,<5.0)
Requires-Dist: typer (>=0.15.4,<0.16.0)
